PyAirwave/PyAirwave.py
PyAirwave/__init__.py
pyairwave-0.0.1.dist-info/LICENSE
pyairwave-0.0.1.dist-info/METADATA
pyairwave-0.0.1.dist-info/WHEEL
pyairwave-0.0.1.dist-info/top_level.txt
pyairwave-0.0.1.dist-info/RECORD
